cleancore/__init__.py
cleancore/audit.py
cleancore/engine.py
cleancore/report.py
cleancore/rules.py
cleancore/transform.py
cleancore-0.1.3.dist-info/licenses/LICENSE
cleancore-0.1.3.dist-info/METADATA
cleancore-0.1.3.dist-info/WHEEL
cleancore-0.1.3.dist-info/top_level.txt
cleancore-0.1.3.dist-info/RECORD
