Metadata-Version: 2.4
Name: cleancore
Version: 0.1.3
Summary: A dependency-free data audit and cleaning framework
Author-email: Sidra Saqlain <sidrasaqlain11@gmail.com>
License: MIT
Classifier: Programming Language :: Python :: 3
Classifier: License :: OSI Approved :: MIT License
Classifier: Operating System :: OS Independent
Requires-Python: >=3.8
License-File: LICENSE
Dynamic: license-file
